projet/__init__.py
projet/algo_genetique.py
projet/background.py
projet/common_functions.py
projet/lastphoto.py
projet/mainGUI.py
projet/neural_network_function.py
projet/neural_network_main.py
projet/select_p.py
projet/suspect_p1.py
projet/suspect_p2.py
Portrait_Robot_G5-0.0.6.dist-info/LICENSE
Portrait_Robot_G5-0.0.6.dist-info/METADATA
Portrait_Robot_G5-0.0.6.dist-info/WHEEL
Portrait_Robot_G5-0.0.6.dist-info/top_level.txt
Portrait_Robot_G5-0.0.6.dist-info/RECORD
