Metadata-Version: 2.1
Name: Portrait-Robot-G5
Version: 0.0.6
Summary: 4BIM project by group 5
Home-page: https://github.com/Lina-ouaret/Project_4bim
Author: Canjura, Loisel, Ouaret, Gaun, Valente
Author-email: maceovalente@gmail.com
License: UNKNOWN
Platform: UNKNOWN
Classifier: Programming Language :: Python :: 3
Classifier: License :: OSI Approved :: GNU General Public License v3 (GPLv3)
Classifier: Operating System :: OS Independent
License-File: LICENSE
